{
  "unversionedId": "User Guide/Alerts/Rule Sets",
  "id": "version-2.2.2/User Guide/Alerts/Rule Sets",
  "title": "Rules",
  "description": "Rule Sets Tab",
  "source": "@site/versioned_docs/version-2.2.2/04-User Guide/Alerts/Rule Sets.md",
  "sourceDirName": "04-User Guide/Alerts",
  "slug": "/User Guide/Alerts/Rule Sets",
  "permalink": "/2.2.2/User Guide/Alerts/Rule Sets",
  "draft": false,
  "tags": [],
  "version": "2.2.2",
  "lastUpdatedAt": 1682340126,
  "formattedLastUpdatedAt": "24 Apr 2023",
  "frontMatter": {
    "description": "Rule Sets Tab"
  },
  "sidebar": "docs",
  "previous": {
    "title": "Alerts Table",
    "permalink": "/2.2.2/User Guide/Alerts/Alerts Table"
  },
  "next": {
    "title": "Configuration",
    "permalink": "/2.2.2/User Guide/Configuration/"
  }
}