{
  "unversionedId": "User Guide/Configuration/General Settings/Maintenance Mode",
  "id": "version-2.4/User Guide/Configuration/General Settings/Maintenance Mode",
  "title": "Maintenance Mode",
  "description": "Maintenance Mode",
  "source": "@site/versioned_docs/version-2.4/04-User Guide/07-Configuration/01-General Settings/03-Maintenance Mode.md",
  "sourceDirName": "04-User Guide/07-Configuration/01-General Settings",
  "slug": "/User Guide/Configuration/General Settings/Maintenance Mode",
  "permalink": "/2.4/User Guide/Configuration/General Settings/Maintenance Mode",
  "draft": false,
  "tags": [],
  "version": "2.4",
  "lastUpdatedAt": 1700558829,
  "formattedLastUpdatedAt": "21 Nov 2023",
  "sidebarPosition": 3,
  "frontMatter": {
    "description": "Maintenance Mode"
  },
  "sidebar": "docs",
  "previous": {
    "title": "Notifications",
    "permalink": "/2.4/User Guide/Configuration/General Settings/Notifications"
  },
  "next": {
    "title": "Diagnostics",
    "permalink": "/2.4/User Guide/Configuration/General Settings/Diagnostics"
  }
}