{
  "unversionedId": "Requirements",
  "id": "version-2.1.0/Requirements",
  "title": "Requirements",
  "description": "Collector hardware requirements",
  "source": "@site/versioned_docs/version-2.1.0/07-Requirements.mdx",
  "sourceDirName": ".",
  "slug": "/Requirements",
  "permalink": "/2.1.0/Requirements",
  "draft": false,
  "tags": [],
  "version": "2.1.0",
  "lastUpdatedAt": 1673276180,
  "formattedLastUpdatedAt": "9 Jan 2023",
  "sidebarPosition": 7,
  "frontMatter": {},
  "sidebar": "docs",
  "previous": {
    "title": "Release notes",
    "permalink": "/2.1.0/Release notes"
  },
  "next": {
    "title": "3rd Party Licenses",
    "permalink": "/2.1.0/3rdpartylicenses"
  }
}